todi/__init__.py
todi/__main__.py
todi/cli.py
todi/constants.py
todi/manager.py
todi/models.py
todi/utils.py
todi/views.py
todi-0.0.3.dist-info/LICENSE
todi-0.0.3.dist-info/METADATA
todi-0.0.3.dist-info/WHEEL
todi-0.0.3.dist-info/entry_points.txt
todi-0.0.3.dist-info/top_level.txt
todi-0.0.3.dist-info/RECORD
