Metadata-Version: 2.1
Name: todi
Version: 0.0.3
Summary: Minimal CLI TODO app.
Home-page: https://github.com/luisgdev/todi
Author: Luis Ch.
Author-email: email@luisch.com
License-File: LICENSE
Requires-Dist: rich
Requires-Dist: tinydb
Requires-Dist: typer
Requires-Dist: typing
